LICENSE.txt
MANIFEST.in
README.md
pyproject.toml
setup.cfg
setup.py
msdm/__init__.py
msdm.egg-info/PKG-INFO
msdm.egg-info/SOURCES.txt
msdm.egg-info/dependency_links.txt
msdm.egg-info/not-zip-safe
msdm.egg-info/requires.txt
msdm.egg-info/top_level.txt
msdm/algorithms/__init__.py
msdm/algorithms/correlatedq.py
msdm/algorithms/entregpolicyiteration.py
msdm/algorithms/friendfoeq.py
msdm/algorithms/fscboundedpolicyiteration.py
msdm/algorithms/fscgradientascent.py
msdm/algorithms/juliapomdps.py
msdm/algorithms/laostar.py
msdm/algorithms/lrtdp.py
msdm/algorithms/multiagentqlearning.py
msdm/algorithms/multichainpolicyiteration.py
msdm/algorithms/nashq.py
msdm/algorithms/pointbasedvalueiteration.py
msdm/algorithms/policyiteration.py
msdm/algorithms/qmdp.py
msdm/algorithms/rmax.py
msdm/algorithms/search.py
msdm/algorithms/tdlearning.py
msdm/algorithms/valueiteration.py
msdm/core/__init__.py
msdm/core/algorithmclasses.py
msdm/core/exceptions.py
msdm/core/assignment/__init__.py
msdm/core/assignment/assignmentmap.py
msdm/core/assignment/assignmentset.py
msdm/core/distributions/__init__.py
msdm/core/distributions/dictdistribution.py
msdm/core/distributions/discretefactortable.py
msdm/core/distributions/distributions.py
msdm/core/distributions/softmaxdistribution.py
msdm/core/mdp/__init__.py
msdm/core/mdp/deterministic_shortest_path.py
msdm/core/mdp/mdp.py
msdm/core/mdp/policy.py
msdm/core/mdp/quickmdp.py
msdm/core/mdp/tables.py
msdm/core/mdp/tabularmdp.py
msdm/core/mdp/tabularpolicy.py
msdm/core/pomdp/__init__.py
msdm/core/pomdp/alphavectorpolicy.py
msdm/core/pomdp/beliefmdp.py
msdm/core/pomdp/finitestatecontroller.py
msdm/core/pomdp/policy.py
msdm/core/pomdp/pomdp.py
msdm/core/pomdp/tabularpomdp.py
msdm/core/posg/__init__.py
msdm/core/posg/posg.py
msdm/core/stochasticgame/__init__.py
msdm/core/stochasticgame/stochasticgame.py
msdm/core/stochasticgame/tabularstochasticgame.py
msdm/core/stochasticgame/policy/__init__.py
msdm/core/stochasticgame/policy/policy.py
msdm/core/stochasticgame/policy/tabularpolicy.py
msdm/core/table/__init__.py
msdm/core/table/table.py
msdm/core/table/tableindex.py
msdm/core/table/tablemisc.py
