Metadata-Version: 2.1
Name: msdm
Version: 0.10
Summary: Models of sequential decision making
Home-page: https://github.com/markkho/msdm
Author: Mark Ho
Author-email: mark.ho.cs@gmail.com
License: MIT
Download-URL: https://github.com/markkho/msdm/archive/refs/tags/v0.10.tar.gz
Keywords: reinforcement learning,planning,cognitive science
Platform: UNKNOWN
Classifier: Development Status :: 3 - Alpha
Classifier: License :: OSI Approved :: MIT License
Classifier: Programming Language :: Python :: 3
Classifier: Programming Language :: Python :: 3.7
Classifier: Programming Language :: Python :: 3.8
Classifier: Programming Language :: Python :: 3.9
